{
  "manifestVersion": "3.2",
  "admin": {
    "address": "0x565B9FAff2bf814796F30be062fdB4cB97FDB7d1",
    "txHash": "0xf194ba82304199be4bb857b619ec3aa67d5a5b005acd5738f58f2de49e7df84b"
  },
  "proxies": [
    {
      "address": "0xeB93352d4fD4052177426ccC85783b39bF41ebf0",
      "txHash": "0x9eeb2fd2523f5946bc005f5121bca1d0b5cabadb87cb2d8fbd2993b81b42ca49",
      "kind": "transparent"
    }
  ],
  "impls": {
    "a494170a4841339890a455c9faebcaaf136de929e6c66ac2bc3607d9de9c7573": {
      "address": "0x6BE6d318322bade25Ac45435D1EB7D85c32a3378",
      "txHash": "0x0ed069f2a89c905de90470858ba7d624efd51ad800f90ff23e81878a011a31bf",
      "layout": {
        "solcVersion": "0.8.7",
        "storage": [
          {
            "label": "_initialized",
            "offset": 0,
            "slot": "0",
            "type": "t_uint8",
            "contract": "Initializable",
            "src": "@openzeppelin/contracts-upgradeable/proxy/utils/Initializable.sol:62",
            "retypedFrom": "bool"
          },
          {
            "label": "_initializing",
            "offset": 1,
            "slot": "0",
            "type": "t_bool",
            "contract": "Initializable",
            "src": "@openzeppelin/contracts-upgradeable/proxy/utils/Initializable.sol:67"
          },
          {
            "label": "__gap",
            "offset": 0,
            "slot": "1",
            "type": "t_array(t_uint256)50_storage",
            "contract": "ContextUpgradeable",
            "src": "@openzeppelin/contracts-upgradeable/utils/ContextUpgradeable.sol:36"
          },
          {
            "label": "_owner",
            "offset": 0,
            "slot": "51",
            "type": "t_address",
            "contract": "OwnableUpgradeable",
            "src": "@openzeppelin/contracts-upgradeable/access/OwnableUpgradeable.sol:22"
          },
          {
            "label": "__gap",
            "offset": 0,
            "slot": "52",
            "type": "t_array(t_uint256)49_storage",
            "contract": "OwnableUpgradeable",
            "src": "@openzeppelin/contracts-upgradeable/access/OwnableUpgradeable.sol:94"
          },
          {
            "label": "addressDeposits",
            "offset": 0,
            "slot": "101",
            "type": "t_mapping(t_address,t_uint8)",
            "contract": "Mixer",
            "src": "contracts/Mixer.sol:12"
          },
          {
            "label": "currentContract",
            "offset": 0,
            "slot": "102",
            "type": "t_address_payable",
            "contract": "Mixer",
            "src": "contracts/Mixer.sol:13"
          }
        ],
        "types": {
          "t_address": {
            "label": "address",
            "numberOfBytes": "20"
          },
          "t_address_payable": {
            "label": "address payable",
            "numberOfBytes": "20"
          },
          "t_array(t_uint256)49_storage": {
            "label": "uint256[49]",
            "numberOfBytes": "1568"
          },
          "t_array(t_uint256)50_storage": {
            "label": "uint256[50]",
            "numberOfBytes": "1600"
          },
          "t_bool": {
            "label": "bool",
            "numberOfBytes": "1"
          },
          "t_mapping(t_address,t_uint8)": {
            "label": "mapping(address => uint8)",
            "numberOfBytes": "32"
          },
          "t_uint256": {
            "label": "uint256",
            "numberOfBytes": "32"
          },
          "t_uint8": {
            "label": "uint8",
            "numberOfBytes": "1"
          }
        }
      }
    },
    "6b40ce8cf6d30a70962895d52d6ebf299df5f7797edafe8d427b2ea4c9adafa6": {
      "address": "0x07752Bb1FAdF24dD25d6ae9CDb06A0eFc4a2Cbb5",
      "txHash": "0x5fcc3db20c1106f807c78909b03cb97f79429220a9f0c26578b7a1902708b821",
      "layout": {
        "solcVersion": "0.8.7",
        "storage": [
          {
            "label": "_initialized",
            "offset": 0,
            "slot": "0",
            "type": "t_uint8",
            "contract": "Initializable",
            "src": "@openzeppelin/contracts-upgradeable/proxy/utils/Initializable.sol:62",
            "retypedFrom": "bool"
          },
          {
            "label": "_initializing",
            "offset": 1,
            "slot": "0",
            "type": "t_bool",
            "contract": "Initializable",
            "src": "@openzeppelin/contracts-upgradeable/proxy/utils/Initializable.sol:67"
          },
          {
            "label": "__gap",
            "offset": 0,
            "slot": "1",
            "type": "t_array(t_uint256)50_storage",
            "contract": "ContextUpgradeable",
            "src": "@openzeppelin/contracts-upgradeable/utils/ContextUpgradeable.sol:36"
          },
          {
            "label": "_owner",
            "offset": 0,
            "slot": "51",
            "type": "t_address",
            "contract": "OwnableUpgradeable",
            "src": "@openzeppelin/contracts-upgradeable/access/OwnableUpgradeable.sol:22"
          },
          {
            "label": "__gap",
            "offset": 0,
            "slot": "52",
            "type": "t_array(t_uint256)49_storage",
            "contract": "OwnableUpgradeable",
            "src": "@openzeppelin/contracts-upgradeable/access/OwnableUpgradeable.sol:94"
          },
          {
            "label": "addressDeposits",
            "offset": 0,
            "slot": "101",
            "type": "t_mapping(t_address,t_uint8)",
            "contract": "Mixer",
            "src": "contracts/Mixer.sol:12"
          },
          {
            "label": "currentContract",
            "offset": 0,
            "slot": "102",
            "type": "t_address_payable",
            "contract": "Mixer",
            "src": "contracts/Mixer.sol:13"
          }
        ],
        "types": {
          "t_address": {
            "label": "address",
            "numberOfBytes": "20"
          },
          "t_address_payable": {
            "label": "address payable",
            "numberOfBytes": "20"
          },
          "t_array(t_uint256)49_storage": {
            "label": "uint256[49]",
            "numberOfBytes": "1568"
          },
          "t_array(t_uint256)50_storage": {
            "label": "uint256[50]",
            "numberOfBytes": "1600"
          },
          "t_bool": {
            "label": "bool",
            "numberOfBytes": "1"
          },
          "t_mapping(t_address,t_uint8)": {
            "label": "mapping(address => uint8)",
            "numberOfBytes": "32"
          },
          "t_uint256": {
            "label": "uint256",
            "numberOfBytes": "32"
          },
          "t_uint8": {
            "label": "uint8",
            "numberOfBytes": "1"
          }
        }
      }
    },
    "0dda3287e8bb0ac5390732960242a6270414971dc48bae5673434d47cbf24dd1": {
      "address": "0xE2A318846800Cae5146EA5B593BD9F3c15d5B710",
      "txHash": "0x057ad8dc00cd9533983bfb99c02b8245c7ea68cd16372907ee11e5bccc68313f",
      "layout": {
        "solcVersion": "0.8.7",
        "storage": [
          {
            "label": "_initialized",
            "offset": 0,
            "slot": "0",
            "type": "t_uint8",
            "contract": "Initializable",
            "src": "@openzeppelin/contracts-upgradeable/proxy/utils/Initializable.sol:62",
            "retypedFrom": "bool"
          },
          {
            "label": "_initializing",
            "offset": 1,
            "slot": "0",
            "type": "t_bool",
            "contract": "Initializable",
            "src": "@openzeppelin/contracts-upgradeable/proxy/utils/Initializable.sol:67"
          },
          {
            "label": "__gap",
            "offset": 0,
            "slot": "1",
            "type": "t_array(t_uint256)50_storage",
            "contract": "ContextUpgradeable",
            "src": "@openzeppelin/contracts-upgradeable/utils/ContextUpgradeable.sol:36"
          },
          {
            "label": "_owner",
            "offset": 0,
            "slot": "51",
            "type": "t_address",
            "contract": "OwnableUpgradeable",
            "src": "@openzeppelin/contracts-upgradeable/access/OwnableUpgradeable.sol:22"
          },
          {
            "label": "__gap",
            "offset": 0,
            "slot": "52",
            "type": "t_array(t_uint256)49_storage",
            "contract": "OwnableUpgradeable",
            "src": "@openzeppelin/contracts-upgradeable/access/OwnableUpgradeable.sol:94"
          },
          {
            "label": "addressDeposits",
            "offset": 0,
            "slot": "101",
            "type": "t_mapping(t_address,t_uint8)",
            "contract": "Mixer",
            "src": "contracts/Mixer.sol:12"
          },
          {
            "label": "currentContract",
            "offset": 0,
            "slot": "102",
            "type": "t_address_payable",
            "contract": "Mixer",
            "src": "contracts/Mixer.sol:13"
          }
        ],
        "types": {
          "t_address": {
            "label": "address",
            "numberOfBytes": "20"
          },
          "t_address_payable": {
            "label": "address payable",
            "numberOfBytes": "20"
          },
          "t_array(t_uint256)49_storage": {
            "label": "uint256[49]",
            "numberOfBytes": "1568"
          },
          "t_array(t_uint256)50_storage": {
            "label": "uint256[50]",
            "numberOfBytes": "1600"
          },
          "t_bool": {
            "label": "bool",
            "numberOfBytes": "1"
          },
          "t_mapping(t_address,t_uint8)": {
            "label": "mapping(address => uint8)",
            "numberOfBytes": "32"
          },
          "t_uint256": {
            "label": "uint256",
            "numberOfBytes": "32"
          },
          "t_uint8": {
            "label": "uint8",
            "numberOfBytes": "1"
          }
        }
      }
    }
  }
}
